qt_material-stubs/__init__.pyi
qt_material-stubs/hook-qt_material.pyi
qt_material-stubs/resources/__init__.pyi
qt_material-stubs/resources/generate.pyi
qt_material-stubs/resources/logo/__init__.pyi
qt_material-stubs/resources/source/__init__.pyi
qt_material_stubs-0.1.0.dist-info/WHEEL
qt_material_stubs-0.1.0.dist-info/METADATA
qt_material_stubs-0.1.0.dist-info/RECORD
